engineerquiz/__init__.py
engineerquiz/main.py
engineerquiz/questions.py
engineerquiz-0.0.3.dist-info/LICENSE
engineerquiz-0.0.3.dist-info/METADATA
engineerquiz-0.0.3.dist-info/WHEEL
engineerquiz-0.0.3.dist-info/entry_points.txt
engineerquiz-0.0.3.dist-info/top_level.txt
engineerquiz-0.0.3.dist-info/RECORD
