Metadata-Version: 2.1
Name: engineerquiz
Version: 0.0.3
Summary: The ultimate test of your engineerness
Home-page: https://gitlab.com/jenx/engineerness/
Author: Ivana Kellyerova
Author-email: ivana.kellyerova+engineerquiz@amarion.net
License: MIT
Keywords: quiz
Platform: UNKNOWN
Classifier: Development Status :: 3 - Alpha
Classifier: Intended Audience :: Developers
Classifier: Intended Audience :: End Users/Desktop
Classifier: License :: OSI Approved :: MIT License
Classifier: Natural Language :: English
Classifier: Operating System :: OS Independent
Classifier: Programming Language :: Python
Classifier: Programming Language :: Python :: 3
Classifier: Programming Language :: Python :: 3 :: Only
Classifier: Topic :: Games/Entertainment
Classifier: Topic :: Software Development
Requires-Dist: click (>=7.1.2)
